setup.cfg
setup.py
./spartan/__init__.py
./spartan/blob_ctx.py
./spartan/cloudpickle.py
./spartan/cluster.py
./spartan/config.py
./spartan/master.py
./spartan/node.py
./spartan/util.py
./spartan/worker.py
./spartan/array/__init__.py
./spartan/array/distarray.py
./spartan/array/extent.py
./spartan/array/tile.py
./spartan/expr/__init__.py
./spartan/expr/backend.py
./spartan/expr/base.py
./spartan/expr/builtins.py
./spartan/expr/index.py
./spartan/expr/loop.py
./spartan/expr/map.py
./spartan/expr/ndarray.py
./spartan/expr/optimize.py
./spartan/expr/outer.py
./spartan/expr/reduce.py
./spartan/expr/shuffle.py
./spartan/expr/stencil.py
./spartan/rpc/__init__.py
./spartan/rpc/common.py
./spartan/rpc/zeromq.py
spartan/core.c
spartan.egg-info/PKG-INFO
spartan.egg-info/SOURCES.txt
spartan.egg-info/dependency_links.txt
spartan.egg-info/requires.txt
spartan.egg-info/top_level.txt