Metadata-Version: 1.1
Name: spartan
Version: 0.06
Summary: Distributed Numpy-like arrays.
Home-page: http://github.com/rjpower/spartan
Author: Russell Power
Author-email: russell.power@gmail.com
License: UNKNOWN
Platform: UNKNOWN
Classifier: Development Status :: 4 - Beta
Classifier: Environment :: Other Environment
Classifier: Intended Audience :: Developers
Classifier: License :: OSI Approved :: BSD License
Classifier: Operating System :: POSIX
Classifier: Programming Language :: C++
Classifier: Programming Language :: Python
Classifier: Programming Language :: Python :: 2.6
Classifier: Programming Language :: Python :: 2.7
